promising/__init__.py
promising-0.0.0.dist-info/METADATA
promising-0.0.0.dist-info/WHEEL
promising-0.0.0.dist-info/licenses/LICENSE
promising-0.0.0.dist-info/RECORD
