Metadata-Version: 2.4
Name: promising
Version: 0.0.0
Summary: TODO
Author-email: Oleksandr Tereshchenko <toporok@gmail.com>
License: MIT
License-File: LICENSE
Requires-Python: >=3.10
Requires-Dist: pydantic<3.0.0,>=2.0.0
Provides-Extra: dev
Requires-Dist: black; extra == 'dev'
Requires-Dist: hatch; extra == 'dev'
Requires-Dist: ipython; extra == 'dev'
Requires-Dist: jupyterlab; extra == 'dev'
Requires-Dist: notebook; extra == 'dev'
Requires-Dist: pre-commit; extra == 'dev'
Requires-Dist: pylint; extra == 'dev'
Requires-Dist: pytest; extra == 'dev'
Requires-Dist: pytest-asyncio; extra == 'dev'
Requires-Dist: pytest-cov; extra == 'dev'
Requires-Dist: pytest-dotenv; extra == 'dev'
Requires-Dist: python-dotenv; extra == 'dev'
